prelapse/__init__.py
prelapse/__main__.py
prelapse/_version.py
prelapse/pylintrc
prelapse/common/__init__.py
prelapse/common/_init_functions.py
prelapse/common/shell.py
prelapse/common/utility_functions.py
prelapse/completions/bash/prelapse
prelapse/configs/__init__.py
prelapse/configs/configs.py
prelapse/examples/generate-example-images-and-play.py
prelapse/genconfig/__init__.py
prelapse/genconfig/argument_parser.py
prelapse/genconfig/lapse_generator.py
prelapse/info/__init__.py
prelapse/info/argument_parser.py
prelapse/info/info.py
prelapse/modifier/__init__.py
prelapse/modifier/argument_parser.py
prelapse/modifier/group_modifier.py
prelapse/modifier/image_modifier.py
prelapse/modifier/label_modifier.py
prelapse/modifier/lapse_modifier.py
prelapse/runner/__init__.py
prelapse/runner/argument_parser.py
prelapse/runner/label_processor.py
prelapse/runner/lapse_runner.py
prelapse/runner/timing_builder.py
prelapse/tests/label_processor_test.py
prelapse-0.2.3.data/data/share/bash-completion/completions/prelapse
prelapse-0.2.3.dist-info/licenses/LICENSE
prelapse-0.2.3.dist-info/METADATA
prelapse-0.2.3.dist-info/WHEEL
prelapse-0.2.3.dist-info/entry_points.txt
prelapse-0.2.3.dist-info/top_level.txt
prelapse-0.2.3.dist-info/RECORD
