Metadata-Version: 2.4
Name: prelapse
Version: 0.2.3
Summary: prelapse is a text based Python toolbox designed to help creating image sequence videos in sync with audio (e.g. slide shows, CG renders, stop motion animation, timelapses and hyperlapses), using ffmpeg/ffplay, Audacity and optionally ImageMagick.
Author-email: PeteHemery <prelapse.founder066@passinbox.com>
Project-URL: Homepage, https://github.com/PeteHemery/prelapse
Keywords: prelapse,python,ffmpeg,ffplay,audacity,imagemagick,stop motion,timelapse,hyperlapse,motion picture,image sequence,image sequencer,image sequences,video editor,non-linear video editor
Classifier: Development Status :: 4 - Beta
Classifier: License :: OSI Approved :: GNU Affero General Public License v3 or later (AGPLv3+)
Classifier: Intended Audience :: Developers
Classifier: Topic :: Artistic Software
Classifier: Topic :: Multimedia :: Video :: Non-Linear Editor
Classifier: Operating System :: OS Independent
Classifier: Programming Language :: Python
Classifier: Programming Language :: Python :: 2.7
Classifier: Programming Language :: Python :: 3
Requires-Python: >=2.7,>=3.0
License-File: LICENSE
Dynamic: license-file
